[
  {
    "line": 2,
    "elements": [
      {
        "start_timestamp": "2021-07-14T04:31:17.748Z",
        "before": [
          {
            "result": {
              "duration": 10320000000,
              "status": "passed"
            },
            "match": {
              "location": "com.expedia.base.Hook.beforeEachScenario()"
            }
          }
        ],
        "line": 5,
        "name": "Successfully rent a car in Madison WI",
        "description": "",
        "id": "flight;successfully-rent-a-car-in-madison-wi",
        "after": [
          {
            "result": {
              "duration": 2792000000,
              "status": "passed"
            },
            "match": {
              "location": "com.expedia.base.Hook.afterEachScenario()"
            }
          }
        ],
        "type": "scenario",
        "keyword": "Scenario",
        "steps": [
          {
            "result": {
              "duration": 442000000,
              "status": "passed"
            },
            "line": 6,
            "name": "user selects \"Cars\" rental tab",
            "match": {
              "arguments": [
                {
                  "val": "\"Cars\"",
                  "offset": 13
                }
              ],
              "location": "com.expedia.stepDefinitions.CarsSteps.userSelectsRentalTab(java.lang.String)"
            },
            "keyword": "Given "
          },
          {
            "result": {
              "duration": 2727000000,
              "status": "passed"
            },
            "line": 7,
            "name": "user selects pickUp location \"Washington (DCA - Ronald Reagan Washington National)\"",
            "match": {
              "arguments": [
                {
                  "val": "\"Washington (DCA - Ronald Reagan Washington National)\"",
                  "offset": 29
                }
              ],
              "location": "com.expedia.stepDefinitions.CarsSteps.userSelectsPickUpLocation(java.lang.String)"
            },
            "keyword": "Then "
          },
          {
            "result": {
              "duration": 2165000000,
              "status": "passed"
            },
            "line": 8,
            "name": "user selects dropOff location \"Washington (DCA - Ronald Reagan Washington National)\"",
            "match": {
              "arguments": [
                {
                  "val": "\"Washington (DCA - Ronald Reagan Washington National)\"",
                  "offset": 30
                }
              ],
              "location": "com.expedia.stepDefinitions.CarsSteps.userSelectsDropOffLocation(java.lang.String)"
            },
            "keyword": "Then "
          },
          {
            "result": {
              "duration": 1633000000,
              "status": "passed"
            },
            "line": 9,
            "name": "user selects pickUp date \"Aug 31, 2021\"",
            "match": {
              "arguments": [
                {
                  "val": "\"Aug 31, 2021\"",
                  "offset": 25
                }
              ],
              "location": "com.expedia.stepDefinitions.CarsSteps.userSelectsPickUpDate(java.lang.String)"
            },
            "keyword": "Then "
          },
          {
            "result": {
              "duration": 1071000000,
              "status": "passed"
            },
            "line": 10,
            "name": "user selects dropOff date \"Sep 3, 2021\"",
            "match": {
              "arguments": [
                {
                  "val": "\"Sep 3, 2021\"",
                  "offset": 26
                }
              ],
              "location": "com.expedia.stepDefinitions.CarsSteps.userSelectsDropOffDate(java.lang.String)"
            },
            "keyword": "Then "
          },
          {
            "result": {
              "duration": 2681000000,
              "status": "passed"
            },
            "line": 11,
            "name": "user selects pickUp time \"9:30 am\"",
            "match": {
              "arguments": [
                {
                  "val": "\"9:30 am\"",
                  "offset": 25
                }
              ],
              "location": "com.expedia.stepDefinitions.CarsSteps.userSelectsPickUpTime(java.lang.String)"
            },
            "keyword": "Then "
          },
          {
            "result": {
              "duration": 4278000000,
              "status": "passed"
            },
            "line": 12,
            "name": "user selects dropOff time \"12:00 am\"",
            "match": {
              "arguments": [
                {
                  "val": "\"12:00 am\"",
                  "offset": 26
                }
              ],
              "location": "com.expedia.stepDefinitions.CarsSteps.userSelectsDropOffTime(java.lang.String)"
            },
            "keyword": "Then "
          }
        ],
        "tags": [
          {
            "name": "@RentalCar"
          },
          {
            "name": "@Car"
          }
        ]
      }
    ],
    "name": "Flight",
    "description": "",
    "id": "flight",
    "keyword": "Feature",
    "uri": "file:src/test/resources/features/Cars.feature",
    "tags": [
      {
        "name": "@RentalCar",
        "type": "Tag",
        "location": {
          "line": 1,
          "column": 1
        }
      }
    ]
  }
]